flection_dictionary/DictLib.py
flection_dictionary/Filters.py
flection_dictionary/Labels.py
flection_dictionary/Lexeme.py
flection_dictionary/Parser.py
flection_dictionary/__init__.py
flection_dictionary/main.py
flection_dict-0.0.1.dist-info/LICENSE
flection_dict-0.0.1.dist-info/METADATA
flection_dict-0.0.1.dist-info/WHEEL
flection_dict-0.0.1.dist-info/top_level.txt
flection_dict-0.0.1.dist-info/RECORD
