Metadata-Version: 2.1
Name: flection-dict
Version: 0.0.1
Summary: Library allows quick and convenient flection finding.
Home-page: https://github.com/twistzzmc/Dictionary
Author: Michał Szczepaniak
Author-email: michal.szczepaniak1999@gmail.com
License: UNKNOWN
Platform: UNKNOWN
Classifier: Programming Language :: Python :: 3
Classifier: License :: OSI Approved :: MIT License
Classifier: Operating System :: OS Independent
Requires-Python: >=3.6
Requires-Dist: marisa-trie
